my_hello_lib/__init__.py
my_hello_lib/hello.py
my_hello_lib_velsankar-0.1.0.dist-info/METADATA
my_hello_lib_velsankar-0.1.0.dist-info/WHEEL
my_hello_lib_velsankar-0.1.0.dist-info/top_level.txt
my_hello_lib_velsankar-0.1.0.dist-info/RECORD
