Metadata-Version: 2.1
Name: my-hello-lib-velsankar
Version: 0.1.0
Summary: A simple hello world logging library
Author: Your Name
Requires-Python: >=3.7
